{
    "id": 109974222,
    "name": "panadol extra",
    "author": "gltdem",
    "creators": ["gltdem"],
    "verifier": "gltdem",
    "verification": "https://youtu.be/D6AMZQHmPmU?feature=shared",
    "percentToQualify": "100",
    "password": "Free To Copy",
    "records": [
        {
           "user": "TimmyTheThirddd",	
           "percent": 100,
           "hz": 360
       },
       {
        "user": "Animized",
        "link": "https://youtu.be/gUfK5V4c3TM",	
        "percent": 100,
        "hz": 360
    }
  ]
} 
